examples/serve/demo/compute_extra_vars.py
examples/serve/demo/resample_in_time.py
examples/serve/panels-demo/compute_indexes.py
examples/serve/panels-demo/demo_panels/__init__.py
examples/serve/panels-demo/demo_panels/panel_demo.py
examples/serve/panels-demo/demo_panels/panel_histo2d.py
examples/serve/panels-demo/demo_panels/panel_spectrum.py
scripts/update-copyright.py
xcube/__init__.py
xcube/constants.py
xcube/plugin.py
xcube/version.py
xcube/cli/__init__.py
xcube/cli/benchmark.py
xcube/cli/chunk.py
xcube/cli/common.py
xcube/cli/compute.py
xcube/cli/dump.py
xcube/cli/extract.py
xcube/cli/gen.py
xcube/cli/gen2.py
xcube/cli/genpts.py
xcube/cli/grid.py
xcube/cli/io.py
xcube/cli/level.py
xcube/cli/main.py
xcube/cli/optimize.py
xcube/cli/patch.py
xcube/cli/prune.py
xcube/cli/rectify.py
xcube/cli/resample.py
xcube/cli/serve.py
xcube/cli/vars2dim.py
xcube/cli/verify.py
xcube/cli/versions.py
xcube/core/__init__.py
xcube/core/ancvar.py
xcube/core/chunk.py
xcube/core/chunkstore.py
xcube/core/compute.py
xcube/core/dsio.py
xcube/core/dump.py
xcube/core/evaluate.py
xcube/core/extract.py
xcube/core/geom.py
xcube/core/level.py
xcube/core/maskset.py
xcube/core/new.py
xcube/core/normalize.py
xcube/core/optimize.py
xcube/core/reproject.py
xcube/core/schema.py
xcube/core/select.py
xcube/core/sentinel3.py
xcube/core/subsampling.py
xcube/core/tile.py
xcube/core/tilingscheme.py
xcube/core/timecoord.py
xcube/core/timeseries.py
xcube/core/timeslice.py
xcube/core/unchunk.py
xcube/core/update.py
xcube/core/vars2dim.py
xcube/core/verify.py
xcube/core/xarray.py
xcube/core/byoa/__init__.py
xcube/core/byoa/config.py
xcube/core/byoa/constants.py
xcube/core/byoa/fileset.py
xcube/core/gen/__init__.py
xcube/core/gen/config.py
xcube/core/gen/defaults.py
xcube/core/gen/gen.py
xcube/core/gen/iproc.py
xcube/core/gen2/__init__.py
xcube/core/gen2/config.py
xcube/core/gen2/error.py
xcube/core/gen2/generator.py
xcube/core/gen2/processor.py
xcube/core/gen2/progress.py
xcube/core/gen2/request.py
xcube_core-1.13.0.dist-info/licenses/LICENSE
xcube_core-1.13.0.dist-info/METADATA
xcube_core-1.13.0.dist-info/WHEEL
xcube_core-1.13.0.dist-info/entry_points.txt
xcube_core-1.13.0.dist-info/top_level.txt
xcube_core-1.13.0.dist-info/RECORD
